lpais/__init__.py
lpais/ais.py
lpais-0.0.2.dist-info/METADATA
lpais-0.0.2.dist-info/RECORD
lpais-0.0.2.dist-info/WHEEL
lpais-0.0.2.dist-info/top_level.txt
tests/__init__.py
tests/test_ais.py
tests/test_pep8.py
