Metadata-Version: 2.1
Name: lpais
Version: 0.0.2
Summary: use libais to decode ais, replacing ais.stream
Home-page: https://github.com/loicpw/lpais
Author: Loïc Peron
Author-email: peronloic.us@gmail.com
License: MIT License
Download-URL: https://github.com/loicpw/lpais.git
Platform: UNKNOWN
Classifier: Development Status :: 3 - Alpha
Classifier: Intended Audience :: Developers
Classifier: License :: OSI Approved :: MIT License
Classifier: Natural Language :: English
Classifier: Programming Language :: Python
Classifier: Programming Language :: Python :: 3.6
Classifier: Programming Language :: Python :: 3.7
Requires-Dist: libais
